hubstudio/__init__.py
hubstudio/main.py
hubstudio-0.4.dist-info/METADATA
hubstudio-0.4.dist-info/WHEEL
hubstudio-0.4.dist-info/top_level.txt
hubstudio-0.4.dist-info/RECORD
